pryvacy/__init__.py
pryvacy/access_policy.py
pryvacy/context.py
pryvacy/decorators/__init__.py
pryvacy/decorators/access_decorators/__init__.py
pryvacy/decorators/pryvacy_decorator/__init__.py
pryvacy/decorators/pryvacy_decorator/instance_methods.py
pryvacy/decorators/pryvacy_decorator/nested_classes.py
pryvacy/decorators/utils.py
pryvacy-0.1.4.dist-info/LICENSE
pryvacy-0.1.4.dist-info/METADATA
pryvacy-0.1.4.dist-info/WHEEL
pryvacy-0.1.4.dist-info/RECORD
