Metadata-Version: 2.1
Name: pryvacy
Version: 0.1.4
Summary: A set of access control descriptors for methods and nested classes
Author: Huy-DNA
Author-email: huydo862003@gmail.com
Requires-Python: >=3.10,<4.0
Classifier: Programming Language :: Python :: 3
Classifier: Programming Language :: Python :: 3.10
Classifier: Programming Language :: Python :: 3.11
Classifier: Programming Language :: Python :: 3.12
